MANIFEST.in
README.md
setup.py
jot/__init__.py
jot/crypto.py
jot/jws.py
jot/jwt.py
jot.egg-info/PKG-INFO
jot.egg-info/SOURCES.txt
jot.egg-info/dependency_links.txt
jot.egg-info/not-zip-safe
jot.egg-info/top_level.txt