Metadata-Version: 1.0
Name: jot
Version: 0.2
Summary: JSON Web Tokens
Home-page: https://github.com/markrcote/jot
Author: Mark Côté
Author-email: mcote@mozilla.com
License: MPL 2.0
Platform: UNKNOWN
